app/__init__.py
app/extras.py
app/precommit.hook
app/scripts.py
precommit_hook-0.1.8.data/scripts/precommit.hook
precommit_hook-0.1.8.dist-info/METADATA
precommit_hook-0.1.8.dist-info/RECORD
precommit_hook-0.1.8.dist-info/WHEEL
precommit_hook-0.1.8.dist-info/top_level.txt
