Metadata-Version: 2.1
Name: precommit-hook
Version: 0.1.8
Summary: Auto check quality of python code before shipping
Home-page: https://github.com/collin5/precommit-hook
Author: Collins Abitekaniza
Author-email: abtcolns@gmail.com
License: MIT
Platform: any
Provides-Extra: dev
Requires-Dist: flake8 (==3.5.0)
Provides-Extra: dev
Requires-Dist: certifi (==2018.4.16); extra == 'dev'
Requires-Dist: chardet (==3.0.4); extra == 'dev'
Requires-Dist: coverage (==4.5.1); extra == 'dev'
Requires-Dist: coveralls (==1.3.0); extra == 'dev'
Requires-Dist: docopt (==0.6.2); extra == 'dev'
Requires-Dist: idna (==2.7); extra == 'dev'
Requires-Dist: nose (==1.3.7); extra == 'dev'
Requires-Dist: requests (==2.19.1); extra == 'dev'
Requires-Dist: urllib3 (==1.22); extra == 'dev'
